test_utils/__init__.py
test_utils/api/__init__.py
test_utils/api/api.py
sfdc_test-2.0.0.dist-info/METADATA
sfdc_test-2.0.0.dist-info/WHEEL
sfdc_test-2.0.0.dist-info/top_level.txt
sfdc_test-2.0.0.dist-info/RECORD
