Metadata-Version: 2.1
Name: sfdc-test
Version: 2.0.0
Summary: just a test package
Author: Nick Le Mouton
Author-email: nlemouton@salesforce.com
Classifier: Programming Language :: Python :: 3
Classifier: Operating System :: Unix
Requires-Python: >=3.6
